[
  {
    "groupId": "dk_category_platform",
      "kits": [
          {
              "allClassName": "com.didichuxing.doraemonkit.kit.network.MockKit",
              "checked": true,
              "innerKitId": "dokit_sdk_platform_ck_mock"
          },
          {
              "allClassName": "com.didichuxing.doraemonkit.kit.health.HealthKit",
              "checked": true,
              "innerKitId": "dokit_sdk_platform_ck_health"
          },
          {
              "allClassName": "com.didichuxing.doraemonkit.kit.filemanager.FileTransferKit",
              "checked": true,
              "innerKitId": "dokit_sdk_platform_ck_filetransfer"
          },
          {
              "allClassName": "com.didichuxing.doraemonkit.kit.mc.MultiControlKitTest",
              "checked": true,
              "innerKitId": "dokit_sdk_platform_ck_mc_test"
          },
          {
              "allClassName": "com.didichuxing.doraemonkit.kit.connect.DoKitStudioConnectKit",
              "checked": true,
              "innerKitId": "dokit_sdk_platform_ck_dokit_connect"
          },
          {
              "allClassName": "com.didichuxing.doraemonkit.kit.dokitforweb.AutoService",
              "checked": true,
              "innerKitId": "dokit_sdk_platform_ck_dokit_for_web"
          },
          {
              "allClassName": "com.didichuxing.doraemonkit.kit.mc.MultiControlKit",
              "checked": true,
              "innerKitId": "dokit_sdk_platform_ck_mc"
          },
          {
              "allClassName": "com.didichuxing.doraemonkit.kit.autotest.AutoTestControlKit",
              "checked": true,
              "innerKitId": "dokit_sdk_platform_ck_autotest"
          },
          {
              "allClassName": "com.kronos.dokit.pthread.PThreadKit",
              "checked": true,
              "innerKitId": "dokit_sdk_platform_thread_hook"
          }
      ]
  },
  {
    "groupId": "dk_category_comms",
    "kits": [
      {
        "allClassName": "com.didichuxing.doraemonkit.kit.sysinfo.SysInfoKit",
        "checked": true,
        "innerKitId": "dokit_sdk_comm_ck_appinfo"
      },
      {
        "allClassName": "com.didichuxing.doraemonkit.kit.sysinfo.ThirdLibInfoKit",
        "checked": true,
        "innerKitId": "dokit_sdk_comm_ck_thirdlibinfo"
      },
      {
        "allClassName": "com.didichuxing.doraemonkit.kit.sysinfo.DevelopmentPageKit",
        "checked": true,
        "innerKitId": "dokit_sdk_comm_ck_devpage"
      },
      {
        "allClassName": "com.didichuxing.doraemonkit.kit.sysinfo.LocalLangKit",
        "checked": true,
        "innerKitId": "dokit_sdk_comm_ck_local_lang"
      },
      {
        "allClassName": "com.didichuxing.doraemonkit.kit.fileexplorer.FileExplorerKit",
        "checked": true,
        "innerKitId": "dokit_sdk_comm_ck_sandbox"
      },
      {
        "allClassName": "com.didichuxing.doraemonkit.kit.webdoor.WebDoorKit",
        "checked": true,
        "innerKitId": "dokit_sdk_comm_ck_h5"
      },
      {
        "allClassName": "com.didichuxing.doraemonkit.kit.dataclean.DataCleanKit",
        "checked": true,
        "innerKitId": "dokit_sdk_comm_ck_cache"
      },
      {
        "allClassName": "com.didichuxing.doraemonkit.kit.loginfo.LogInfoKit",
        "checked": true,
        "innerKitId": "dokit_sdk_comm_ck_log"
      },
      {
        "allClassName": "com.didichuxing.doraemonkit.kit.h5_help.H5Kit",
        "checked": true,
        "innerKitId": "dokit_sdk_comm_ck_h5kit"
      }
    ]
  },
  {
    "groupId": "dk_category_lbs",
    "kits": [
      {
        "allClassName": "com.didichuxing.doraemonkit.kit.gpsmock.GpsMockKit",
        "checked": true,
        "innerKitId": "dokit_sdk_comm_ck_gps"
      },
      {
        "allClassName": "com.didichuxing.doraemonkit.kit.lbs.manual.PosAdjustKit",
        "checked": true,
        "innerKitId": "dokit_sdk_lbs_ck_pos_adjust"
      },
      {
        "allClassName": "com.didichuxing.doraemonkit.kit.lbs.route.RealNavMockKit",
        "checked": true,
        "innerKitId": "dokit_sdk_lbs_ck_nav"
      }
    ]
  },
  {
    "groupId": "dk_category_weex",
    "kits": [
      {
        "allClassName": "com.didichuxing.doraemonkit.weex.log.WeexLogKit",
        "checked": true,
        "innerKitId": "dokit_sdk_weex_ck_log"
      },
      {
        "allClassName": "com.didichuxing.doraemonkit.weex.storage.WeexStorageKit",
        "checked": true,
        "innerKitId": "dokit_sdk_weex_ck_storage"
      },
      {
        "allClassName": "com.didichuxing.doraemonkit.weex.info.WeexInfoKit",
        "checked": true,
        "innerKitId": "dokit_sdk_weex_ck_info"
      },
      {
        "allClassName": "com.didichuxing.doraemonkit.weex.devtool.WeexDevToolKit",
        "checked": true,
        "innerKitId": "dokit_sdk_weex_ck_devtool"
      }
    ]
  },
  {
    "groupId": "dk_category_performance",
    "kits": [
      {
        "allClassName": "com.didichuxing.doraemonkit.kit.parameter.frameInfo.FrameInfoKit",
        "checked": true,
        "innerKitId": "dokit_sdk_performance_ck_fps"
      },
      {
        "allClassName": "com.didichuxing.doraemonkit.kit.parameter.cpu.CpuKit",
        "checked": true,
        "innerKitId": "dokit_sdk_performance_ck_cpu"
      },
      {
        "allClassName": "com.didichuxing.doraemonkit.kit.parameter.ram.RamKit",
        "checked": true,
        "innerKitId": "dokit_sdk_performance_ck_arm"
      },
      {
        "allClassName": "com.didichuxing.doraemonkit.kit.network.NetworkKit",
        "checked": true,
        "innerKitId": "dokit_sdk_performance_ck_network"
      },
      {
        "allClassName": "com.didichuxing.doraemonkit.kit.crash.CrashCaptureKit",
        "checked": true,
        "innerKitId": "dokit_sdk_comm_ck_crash"
      },
      {
        "allClassName": "com.didichuxing.doraemonkit.kit.blockmonitor.BlockMonitorKit",
        "checked": true,
        "innerKitId": "dokit_sdk_performance_ck_block"
      },
      {
        "allClassName": "com.didichuxing.doraemonkit.kit.largepicture.LargePictureKit",
        "checked": true,
        "innerKitId": "dokit_sdk_performance_ck_img"
      },
      {
        "allClassName": "com.didichuxing.doraemonkit.kit.weaknetwork.WeakNetworkKit",
        "checked": true,
        "innerKitId": "dokit_sdk_comm_ck_weaknetwork"
      },
      {
        "allClassName": "com.didichuxing.doraemonkit.kit.timecounter.TimeCounterKit",
        "checked": true,
        "innerKitId": "dokit_sdk_performance_ck_open_coast"
      },
      {
        "allClassName": "com.didichuxing.doraemonkit.kit.uiperformance.UIPerformanceKit",
        "checked": true,
        "innerKitId": "dokit_sdk_performance_ck_hierarchy"
      },
      {
        "allClassName": "com.didichuxing.doraemonkit.kit.methodtrace.MethodCostKit",
        "checked": true,
        "innerKitId": "dokit_sdk_performance_ck_method_coast"
      },
      {
        "allClassName": "com.didichuxing.doraemonkit.kit.leakcanary.LeakCanaryKit",
        "checked": true,
        "innerKitId": "dokit_sdk_performance_ck_leak"
      }
    ]
  },
  {
    "groupId": "dk_category_ui",
    "kits": [
      {
        "allClassName": "com.didichuxing.doraemonkit.kit.colorpick.ColorPickerKit",
        "checked": true,
        "innerKitId": "dokit_sdk_ui_ck_color_pick"
      },
      {
        "allClassName": "com.didichuxing.doraemonkit.kit.alignruler.AlignRulerKit",
        "checked": true,
        "innerKitId": "dokit_sdk_ui_ck_aligin_scaleplate"
      },
      {
        "allClassName": "com.didichuxing.doraemonkit.kit.viewcheck.ViewCheckerKit",
        "checked": true,
        "innerKitId": "dokit_sdk_ui_ck_widget"
      },
      {
        "allClassName": "com.didichuxing.doraemonkit.kit.layoutborder.LayoutBorderKit",
        "checked": true,
        "innerKitId": "dokit_sdk_ui_ck_border"
      }
    ]
  }
]
